{
  "short_name": "BB KDS",
  "name": "Bum Bum Cafe | Kitchen Display System",
  "icons": [
    {
      "src": "/icon-192x192.png",
      "sizes": "192x192",
      "type": "image/png",
      "purpose": "any maskable"
    },
    {
      "src": "/icon-512x512.png",
      "sizes": "512x512",
      "type": "image/png",
      "purpose": "any maskable"
    }
  ],
  "start_url": "/kds",
  "background_color": "#050505",
  "theme_color": "#ff5e00",
  "display": "standalone",
  "orientation": "landscape"
}
